odoo8_addon_membership_variable_period-8.0.2.0.0-py2.7-nspkg.pth
odoo_addons/membership_variable_period/__openerp__.py
odoo_addons/membership_variable_period/__init__.py
odoo_addons/membership_variable_period/README.rst
odoo_addons/membership_variable_period/models/product_template.py
odoo_addons/membership_variable_period/models/account_invoice.py
odoo_addons/membership_variable_period/models/__init__.py
odoo_addons/membership_variable_period/i18n/it.po
odoo_addons/membership_variable_period/i18n/es.po
odoo_addons/membership_variable_period/i18n/membership_variable_period.pot
odoo_addons/membership_variable_period/i18n/sl.po
odoo_addons/membership_variable_period/i18n/nl.po
odoo_addons/membership_variable_period/i18n/de.po
odoo_addons/membership_variable_period/i18n/fr.po
odoo_addons/membership_variable_period/i18n/pt_BR.po
odoo_addons/membership_variable_period/views/product_template_views.xml
odoo_addons/membership_variable_period/tests/__init__.py
odoo_addons/membership_variable_period/tests/test_membership_variable_period.py
odoo_addons/membership_variable_period/static/description/icon_main.svg
odoo_addons/membership_variable_period/static/description/icon.svg
odoo_addons/membership_variable_period/static/description/icon.png
odoo8_addon_membership_variable_period-8.0.2.0.0.dist-info/top_level.txt
odoo8_addon_membership_variable_period-8.0.2.0.0.dist-info/WHEEL
odoo8_addon_membership_variable_period-8.0.2.0.0.dist-info/RECORD
odoo8_addon_membership_variable_period-8.0.2.0.0.dist-info/metadata.json
odoo8_addon_membership_variable_period-8.0.2.0.0.dist-info/DESCRIPTION.rst
odoo8_addon_membership_variable_period-8.0.2.0.0.dist-info/METADATA
odoo8_addon_membership_variable_period-8.0.2.0.0.dist-info/namespace_packages.txt
