Metadata-Version: 2.0
Name: odoo8-addon-membership-variable-period
Version: 8.0.2.0.0
Summary: Variable period for memberships
Home-page: https://odoo-community.org/
Author: Tecnativa, Antiun Ingeniería S.L., Serv. Tecnol. Avanzados - Pedro M. Baeza, Odoo Community Association (OCA)
Author-email: support@odoo-community.org
License: AGPL-3
Platform: UNKNOWN
Requires-Dist: odoo (<9.0a,>=8.0a)
Requires-Dist: odoo8-addon-membership-extension
Classifier: Programming Language :: Python :: 2.7
Classifier: Framework :: Odoo
Classifier: License :: OSI Approved :: GNU Affero General Public License v3
